anime_light/__init__.py
anime_light/__main__.py
anime_light/cli/__init__.py
anime_light/cli/commands.py
anime_light/cli/main.py
anime_light/cli/parser.py
anime_light/cli/utils.py
anime_light/core/__init__.py
anime_light/core/converter.py
anime_light-0.3.1.dist-info/entry_points.txt
anime_light-0.3.1.dist-info/LICENSE
anime_light-0.3.1.dist-info/METADATA
anime_light-0.3.1.dist-info/WHEEL
anime_light-0.3.1.dist-info/RECORD
