Metadata-Version: 2.3
Name: anime-light
Version: 0.3.1
Summary: Conversor de anime a resoluciones ligeras (360p/480p/720p/1080p) con FFmpeg
License: MIT
Keywords: anime,video,converter,ffmpeg
Author: Gabriel Baute
Author-email: gabrielbaute@gmail.com
Requires-Python: >=3.8,<4.0
Classifier: License :: OSI Approved :: MIT License
Classifier: Programming Language :: Python :: 3
Classifier: Programming Language :: Python :: 3.8
Classifier: Programming Language :: Python :: 3.9
Classifier: Programming Language :: Python :: 3.10
Classifier: Programming Language :: Python :: 3.11
Classifier: Programming Language :: Python :: 3.12
Classifier: Programming Language :: Python :: 3.13
Requires-Dist: click (>=8.1.0,<9.0.0)
Requires-Dist: rich (>=13.0.0,<14.0.0)
Project-URL: Bug Tracker, https://github.com/gabrielbaute/anime-light/issues
Project-URL: Homepage, https://github.com/gabrielbaute/anime-light
Project-URL: Repository, https://github.com/gabrielbaute/anime-light
